solid_oidc_client/__init__.py
solid_oidc_client/dpop_utils.py
solid_oidc_client/solid_auth_session.py
solid_oidc_client/solid_oidc_client.py
solid_oidc_client/storage.py
solid_oidc_client-0.0.4.dist-info/METADATA
solid_oidc_client-0.0.4.dist-info/WHEEL
solid_oidc_client-0.0.4.dist-info/licenses/LICENSE
solid_oidc_client-0.0.4.dist-info/RECORD
