Metadata-Version: 2.1
Name: solid_oidc_client
Version: 0.0.4
Summary: A solid-OIDC client
Project-URL: Homepage, https://github.com/Otto-AA/solid-oidc-py
Project-URL: Bug Tracker, https://github.com/Otto-AA/solid-oidc-py/issues
Author-email: A_A <21040751+Otto-AA@users.noreply.github.com>
License-File: LICENSE
Classifier: Development Status :: 3 - Alpha
Classifier: License :: OSI Approved :: MIT License
Classifier: Operating System :: OS Independent
Classifier: Programming Language :: Python :: 3
Requires-Python: >=3.7
Requires-Dist: jwcrypto~=1.4.2
Requires-Dist: oic~=1.5.0
Requires-Dist: requests~=2.28.2
